CHANGES.txt
LICENSE.txt
MANIFEST.in
README.txt
ravenc.e4p
setup.cfg
setup.py
stdeb.cfg
.issues/.properties
docs/Makefile
docs/conf.py
docs/howto.rst
docs/index.rst
docs/motivation.rst
docs/overview.rst
docs/todo.rst
ravenc/__init__.py
ravenc/command.py
ravenc/dvd.py
ravenc/encoders.py
ravenc/forms.py
ravenc/ravenc.py
ravenc/utils.py
ravenc.egg-info/PKG-INFO
ravenc.egg-info/SOURCES.txt
ravenc.egg-info/dependency_links.txt
ravenc.egg-info/entry_points.txt
ravenc.egg-info/requires.txt
ravenc.egg-info/top_level.txt
ravenc/resources/__init__.py
ravenc/resources/default_document.png
ravenc/resources/dvd_r.png
ravenc/resources/movies.png
ravenc/resources/ravenc.qrc
ravenc/resources/ravenc_rc.py
ravenc/ui/Ui_br_mainwindow.py
ravenc/ui/__init__.py
ravenc/ui/br_jobdock.py
ravenc/ui/br_mainwindow.py
ravenc/ui/br_mainwindow.ui
share/.directory
share/ravenc.desktop
share/ravenc.xpm