Metadata-Version: 1.1
Name: ravenc
Version: 0.3-beta6
Summary: DVD Ripper and File Transcoder.
Home-page: http://www.electron.me.uk
Author: Geoff Clements
Author-email: geoff@electron.me.uk
License: UNKNOWN
Keywords: dvd transcoding video ripping
Platform: UNKNOWN
Classifier: License :: OSI Approved :: GNU General Public License (GPL)
Classifier: Environment :: X11 Applications
Classifier: Environment :: X11 Applications :: Qt
Classifier: Intended Audience :: End Users/Desktop
Classifier: Natural Language :: English
Classifier: Operating System :: POSIX :: Linux
Classifier: Topic :: Multimedia :: Video
Classifier: Topic :: Multimedia :: Video :: Conversion
